HighResAnalysis/__init__.py
HighResAnalysis/_modidx.py
HighResAnalysis/analyse.py
HighResAnalysis/convert.py
HighResAnalysis/cern/__init__.py
HighResAnalysis/cern/adc.py
HighResAnalysis/cern/calibration.py
HighResAnalysis/cern/converter.py
HighResAnalysis/cern/event_alignment.py
HighResAnalysis/cern/raw.py
HighResAnalysis/cern/ref.py
HighResAnalysis/mod/__init__.py
HighResAnalysis/mod/dut_cuts.py
HighResAnalysis/mod/efficiency.py
HighResAnalysis/mod/ref_cuts.py
HighResAnalysis/mod/reference.py
HighResAnalysis/mod/residuals.py
HighResAnalysis/mod/reso_cuts.py
HighResAnalysis/mod/resolution.py
HighResAnalysis/mod/tel_cuts.py
HighResAnalysis/mod/telescope.py
HighResAnalysis/mod/track_cuts.py
HighResAnalysis/mod/tracks.py
HighResAnalysis/plotting/__init__.py
HighResAnalysis/plotting/binning.py
HighResAnalysis/plotting/draw.py
HighResAnalysis/plotting/fit.py
HighResAnalysis/plotting/html.py
HighResAnalysis/plotting/info.py
HighResAnalysis/plotting/latex.py
HighResAnalysis/plotting/save.py
HighResAnalysis/plotting/utils.py
HighResAnalysis/src/__init__.py
HighResAnalysis/src/analysis.py
HighResAnalysis/src/batch_analysis.py
HighResAnalysis/src/bins.py
HighResAnalysis/src/calibration.py
HighResAnalysis/src/converter.py
HighResAnalysis/src/currents.py
HighResAnalysis/src/cut.py
HighResAnalysis/src/dut.py
HighResAnalysis/src/dut_analysis.py
HighResAnalysis/src/proteus.py
HighResAnalysis/src/raw.py
HighResAnalysis/src/run.py
HighResAnalysis/src/scan.py
HighResAnalysis/src/spreadsheet.py
HighResAnalysis/utility/__init__.py
HighResAnalysis/utility/affine_transformations.py
HighResAnalysis/utility/utils.py
HighResAnalysis-0.0.7.dist-info/.ipynb_checkpoints/PKG-INFO-checkpoint
HighResAnalysis-0.0.7.dist-info/.ipynb_checkpoints/SOURCES-checkpoint.txt
HighResAnalysis-0.0.7.dist-info/.ipynb_checkpoints/dependency_links-checkpoint.txt
HighResAnalysis-0.0.7.dist-info/.ipynb_checkpoints/entry_points-checkpoint.txt
HighResAnalysis-0.0.7.dist-info/.ipynb_checkpoints/not-zip-safe-checkpoint
HighResAnalysis-0.0.7.dist-info/.ipynb_checkpoints/requires-checkpoint.txt
HighResAnalysis-0.0.7.dist-info/.ipynb_checkpoints/top_level-checkpoint.txt
HighResAnalysis-0.0.7.dist-info/LICENSE
HighResAnalysis-0.0.7.dist-info/METADATA
HighResAnalysis-0.0.7.dist-info/WHEEL
HighResAnalysis-0.0.7.dist-info/entry_points.txt
HighResAnalysis-0.0.7.dist-info/top_level.txt
HighResAnalysis-0.0.7.dist-info/RECORD
