Metadata-Version: 2.1
Name: HighResAnalysis
Version: 0.0.7
Summary: Analysis of High Resolution Data from CERN and DESY beam tests
Home-page: https://github.com/dmitryhits/HighResAnalysis
Author: Dmitry Hits
Author-email: dmitry.hits@gmail.com
License: Apache Software License 2.0
Keywords: nbdev jupyter notebook python alignment telescope testbeam
Classifier: Development Status :: 3 - Alpha
Classifier: Intended Audience :: Developers
Classifier: Natural Language :: English
Classifier: Programming Language :: Python :: 3.7
Classifier: Programming Language :: Python :: 3.8
Classifier: Programming Language :: Python :: 3.9
Classifier: Programming Language :: Python :: 3.10
Classifier: License :: OSI Approved :: Apache Software License
Requires-Python: >=3.7
License-File: LICENSE
Requires-Dist: nbdev
Requires-Dist: ipython
Requires-Dist: termcolor
Requires-Dist: numpy
Requires-Dist: uncertainties
Requires-Dist: h5py
Requires-Dist: toml
Requires-Dist: pytz
Requires-Dist: uproot
Requires-Dist: gtts
Requires-Dist: gspread
Requires-Dist: oauth2client
Requires-Dist: awkward
Requires-Dist: progressbar
Requires-Dist: scipy
Requires-Dist: screeninfo
Requires-Dist: fastcore
Provides-Extra: dev
